{
  "num": "1602",
  "name": {
    "ko": "죠나단 죠스타",
    "ja": "ねんどろいど ジョナサン・ジョースター (ねんどろいど じょなさん・じょーすたー)",
    "en": "Nendoroid Jonathan Joestar"
  },
  "series": {
    "ko": "죠죠의 기묘한 모험",
    "ja": "TVアニメ『ジョジョの奇妙な冒険』",
    "en": "JoJo\u0027s Bizarre Adventure"
  },
  "gsc_productNum": 11001,
  "price": 5478,
  "release_date": [
    "2021/11"
  ],
  "image": "https://images.goodsmile.info/cgm/images/product/20210326/11001/82889/large/ff48533d6f6bcf1211eed091a11c4bd7.jpg",
  "gender": "M",
  "set": 191
}