{
  "num": "1656",
  "name": {
    "KO": "A2",
    "JA": "ねんどろいど NieR:Automata A2（ヨルハA型二号） (ねんどろいど にーあ:おーとまた えーとぅ（よるはえーがたにごう）)",
    "EN": "Nendoroid NieR:Automata A2 (YoRHa Type A No. 2)"
  },
  "series": {
    "KO": "니어 오토마타",
    "JA": "NieR:Automata",
    "EN": "NieR:Automata"
  },
  "gsc_productNum": 11553,
  "price": 6600,
  "release_date": [
    "2021/12"
  ],
  "image": "https://images.goodsmile.info/cgm/images/product/20210727/11553/87730/large/e281e55fd385b954c778d6d38a866296.jpg",
  "gender": "여"
}