{
  "gender" : "M",
  "gsc_productNum" : 4000,
  "image" : "https://images.goodsmile.info/cgm/images/product/20130724/4000/25275/large/b5e2cfef5fd78c340f5a5d3b5993c85b.jpg",
  "name" : {
    "en" : "Nendoroid Iron Man Mark 42: Hero’s Edition + Hall of Armor Set (ねんどろいど あいあんまん まーく42 ひーろーず・えでぃしょん+ほーる・おぶ・あーまーせっと)",
    "ja" : "ねんどろいど アイアンマン マーク42 ヒーローズ・エディション+ホール・オブ・アーマーセット (ねんどろいど あいあんまん まーく42 ひーろーず・えでぃしょん+ほーる・おぶ・あーまーせっと)",
    "ko" : "아이언맨 마크42 히어로즈 에디션+홀 오브 아머 세트"
  },
  "num" : "349",
  "price" : 5762,
  "release_date" : [
    "2013/12"
  ],
  "series" : {
    "en" : "Iron Man 3",
    "ja" : "アイアンマン3",
    "ko" : "아이언맨3"
  },
  "set" : 64
}