{
  "gsc_productNum" : 10217,
  "image" : "https://images.goodsmile.info/cgm/images/product/20201012/10217/75608/large/39c4959835568143df1ba1d886570c43.jpg",
  "name" : {
    "en" : "Nendoroid Doll: Outfit Set (Little Red Riding Hood)",
    "ja" : "ねんどろいどどーる おようふくセット 赤ずきんちゃん (ねんどろいどどーる おようふくせっと あかずきんちゃん)",
    "ko" : "빨간망토 로즈 의상"
  },
  "price" : 4000,
  "release_date" : [
    "2021/06"
  ],
  "series" : {
    "en" : "Nendoroid Doll",
    "ja" : "ねんどろいどどーる",
    "ko" : "굿스마일 오리지널"
  },
  "type" : "clothes"
}