{
  "gsc_productNum" : 11875,
  "image" : "https://images.goodsmile.info/cgm/images/product/20211006/11875/90763/large/e65d3acf25ea45cca37b10c520c69813.jpg",
  "name" : {
    "en" : "Nendoroid Doll: Outfit Set (Zenitsu Agatsuma)",
    "ja" : "ねんどろいどどーる おようふくセット 我妻善逸 (ねんどろいどどーる おようふくせっと あがつまぜんいつ)",
    "ko" : "아가츠마 젠이츠 의상"
  },
  "price" : 4200,
  "release_date" : [
    "2022/06"
  ],
  "series" : {
    "en" : "Demon Slayer: Kimetsu no Yaiba",
    "ja" : "鬼滅の刃",
    "ko" : "귀멸의 칼날"
  },
  "type" : "clothes"
}