{
  "gsc_productNum" : 8801,
  "image" : "https://images.goodsmile.info/cgm/images/product/20190918/8801/63707/large/bb4793fb48621b6e04cec1e49ecd46aa.jpg",
  "name" : {
    "en" : "Nendoroid Doll: Outfit Set (Hakama - Girl)",
    "ja" : "ねんどろいどどーる おようふくセット（ハイカラちゃん） (ねんどろいどどーる おようふくせっと（はいからちゃん）)",
    "ko" : "하카마(하이카라짱) 의상"
  },
  "price" : 3700,
  "release_date" : [
    "2020/06"
  ],
  "series" : {
    "en" : "Nendoroid Doll",
    "ja" : "ねんどろいどどーる",
    "ko" : "굿스마일 오리지널"
  },
  "type" : "clothes"
}