{
  "gsc_productNum" : 8893,
  "image" : "https://images.goodsmile.info/cgm/images/product/20191009/8893/64500/large/f3b32b8cbb9c4c751350fb99e99178c8.jpg",
  "name" : {
    "en" : "Nendoroid Doll: Outfit Set (Gryffindor Uniform - Girl)",
    "ja" : "ねんどろいどどーる おようふくセット（グリフィンドール制服：Girl） (ねんどろいどどーる おようふくせっと（ぐりふぃんどーるせいふく：がーる）)",
    "ko" : "그리핀도르 의상(여)"
  },
  "price" : 4200,
  "release_date" : [
    "2020/09"
  ],
  "series" : {
    "en" : "Harry Potter",
    "ja" : "ハリー・ポッター",
    "ko" : "해리포터 시리즈"
  },
  "type" : "clothes"
}