{
  "num": "001",
  "name": {
    "ko": "네코 알퀘이드 - 환장! 수수께끼의 제트 비행 편",
    "ja": "ねんどろいど ネコアルク 「換装！謎のジェット飛行」編 (ねこあるく　ねんどろいど 「かんそう！なぞのじぇっとひこう」へん)",
    "en": "Nendoroid Neko Arc : Convert! Mysterious Jet Flight Edition (ねこあるく　ねんどろいど 「かんそう！などのじぇっとひこう」へん)"
  },
  "series": {
    "ko": "월희",
    "ja": "ネコアルク",
    "en": "Neko Arc"
  },
  "gsc_productNum": 448,
  "price": 3143,
  "release_date": [
    "2007/10"
  ],
  "image": "https://images.goodsmile.info/cgm/images/product/20091023/448/497/large/da9642c61d57c8a2f9622c682ca8ab95.jpg",
  "gender": "F",
  "set": 1
}