{
  "gender" : "F",
  "gsc_productNum" : 2580,
  "image" : "https://images.goodsmile.info/cgm/images/product/20091023/2580/7543/large/3353b5d4c89355377fcbef5d586ca980.jpg",
  "name" : {
    "en" : "Nendoroid Churuya-san (ちゅるやさん ねんどろいど)",
    "ja" : "ねんどろいど ちゅるやさん (ちゅるやさん ねんどろいど)",
    "ko" : "츄루야 상"
  },
  "num" : "083",
  "price" : 3143,
  "release_date" : [
    "2009/12"
  ],
  "series" : {
    "en" : "The Melancholy of Haruhi Suzumiya-chan & Nyoron Churuya-san",
    "ja" : "「涼宮ハルヒちゃんの憂鬱」＆「にょろーんちゅるやさん」",
    "ko" : "뇨롱☆츄루야씨"
  }
}