{
  "gender" : "M",
  "gsc_productNum" : 5948,
  "image" : "https://images.goodsmile.info/cgm/images/product/20160913/5948/41314/large/befdf1db257a0d6d7b6406ca1bf8a8fd.jpg",
  "name" : {
    "en" : "Nendoroid Chuya Nakahara",
    "ja" : "ねんどろいど 中原中也 (ねんどろいど なかはらちゅうや)",
    "ko" : "나카하라 츄야"
  },
  "num" : "676",
  "price" : 4584,
  "release_date" : [
    "2017/04",
    "2017/09",
    "2020/05",
    "2023/09"
  ],
  "series" : {
    "en" : "Bungo Stray Dogs",
    "ja" : "文豪ストレイドッグス",
    "ko" : "문호 스트레이 독스"
  },
  "set" : 137
}