{
  "gender" : "F",
  "gsc_productNum" : 6608,
  "image" : "https://images.goodsmile.info/cgm/images/product/20170725/6608/46736/large/45c63a8ef086d16bc2782fe7ce7cccff.jpg",
  "name" : {
    "en" : "Nendoroid Tomo Kunagisa",
    "ja" : "ねんどろいど 玖渚友 (ねんどろいど くなぎさとも)",
    "ko" : "쿠나기사 토모"
  },
  "num" : "805",
  "price" : 5398,
  "release_date" : [
    "2018/02"
  ],
  "series" : {
    "en" : "The Beheading Cycle: The Blue Savant and the Nonsense Bearer",
    "ja" : "クビキリサイクル 青色サヴァンと戯言遣い",
    "ko" : "헛소리 시리즈"
  },
  "set" : 162
}