{
  "gender" : "M",
  "gsc_productNum" : 7468,
  "image" : "https://images.goodsmile.info/cgm/images/product/20180724/7468/53415/large/b785248e09bbb271db296037ef06d6be.jpg",
  "name" : {
    "en" : "Nendoroid Tomohisa Kitakado",
    "ja" : "ねんどろいど 北門倫毘沙 (ねんどろいど きたかどともひさ)",
    "ko" : "키타카도 토모히사"
  },
  "num" : "966",
  "price" : 5093,
  "release_date" : [
    "2018/11"
  ],
  "series" : {
    "en" : "B-Project: ~ Kodou＊Ambitious ~",
    "ja" : "B-PROJECT ～鼓動＊アンビシャス～",
    "ko" : "B-PROJECT ~고동＊앰비셔스~"
  },
  "set" : 190
}