{
  "gender" : "F",
  "gsc_productNum" : 8444,
  "image" : "https://images.goodsmile.info/cgm/images/product/20190619/8444/61125/large/3879cb61e7a817f4a0b171a39a7f017b.jpg",
  "name" : {
    "en" : "Nendoroid Ashe: Classic Skin Edition",
    "ja" : "ねんどろいど アッシュ クラシックスキン・エディション (ねんどろいど あっしゅ くらしっくすきん・えでぃしょん)",
    "ko" : "애쉬"
  },
  "num" : "1167",
  "price" : 5500,
  "release_date" : [
    "2019/12"
  ],
  "series" : {
    "en" : "Overwatch",
    "ja" : "オーバーウォッチ",
    "ko" : "오버워치"
  },
  "set" : 152
}