{
  "num": "1010b",
  "name": {
    "ko": "미키 마우스 1928 Ver.(컬러)",
    "ja": "ねんどろいど ミッキーマウス 1928 Ver.（カラー） (ねんどろいど みっきーまうす 1928 Ver.（からー）)",
    "en": "Nendoroid Mickey Mouse: 1928 Ver. (Color)"
  },
  "series": {
    "ko": "증기선 윌리",
    "ja": "蒸気船ウィリー",
    "en": "Steamboat Willie"
  },
  "gsc_productNum": 7652,
  "price": 5297,
  "release_date": [
    "2019/05"
  ],
  "image": "https://images.goodsmile.info/cgm/images/product/20180928/7652/54870/large/75cb3406ce918242a7bbb4f76836f368.jpg",
  "gender": "없음"
}