{
  "num": "1025-DX",
  "name": {
    "KO": "헌터♀ 제노라지β 에디션 DX Ver.",
    "JA": "ねんどろいど ハンター♀ ゼノラージβ・エディション DX Ver. (ねんどろいど はんたー♀ ぜのらーじべーた・えでぃしょん DX Ver.)",
    "EN": "Nendoroid Hunter: Female Xeno’jiiva Beta Armor Edition - DX Ver."
  },
  "series": {
    "KO": "몬스터 헌터",
    "JA": "モンスターハンター：ワールド",
    "EN": "MONSTER HUNTER: WORLD"
  },
  "gsc_productNum": 7790,
  "price": 7638,
  "release_date": [
    "2019/06"
  ],
  "image": "https://images.goodsmile.info/cgm/images/product/20181108/7790/55817/large/563be9585bd03ad26c362b27d7ad5d55.jpg",
  "gender": "남"
}